ollama_prompt/__init__.py
ollama_prompt/cli.py
ollama_prompt/models.py
ollama_prompt/session_db.py
ollama_prompt/session_manager.py
ollama_prompt/session_utils.py
ollama_prompt-1.2.0.dist-info/licenses/LICENSE
tests/__init__.py
tests/test_cli_integration.py
tests/test_context_persistence.py
tests/test_directory_syntax.py
tests/test_secure_file.py
tests/test_session_db.py
ollama_prompt-1.2.0.dist-info/METADATA
ollama_prompt-1.2.0.dist-info/WHEEL
ollama_prompt-1.2.0.dist-info/entry_points.txt
ollama_prompt-1.2.0.dist-info/top_level.txt
ollama_prompt-1.2.0.dist-info/RECORD
