Metadata-Version: 2.4
Name: ollama-prompt
Version: 1.2.0
Summary: Ollama CLI prompt tool for local LLM code analysis
Home-page: https://github.com/dansasser/ollama-prompt
Author: Daniel T Sasser II
Requires-Python: >=3.10
License-File: LICENSE
Requires-Dist: ollama
Requires-Dist: llm-fs-tools>=0.1.0
Provides-Extra: mongodb
Requires-Dist: pymongo>=4.0.0; extra == "mongodb"
Provides-Extra: test
Requires-Dist: pytest>=7.0.0; extra == "test"
Requires-Dist: pytest-cov>=4.0.0; extra == "test"
Provides-Extra: dev
Requires-Dist: pytest>=7.0.0; extra == "dev"
Requires-Dist: pytest-cov>=4.0.0; extra == "dev"
Requires-Dist: ruff>=0.1.0; extra == "dev"
Dynamic: home-page
Dynamic: license-file
Dynamic: requires-python
